odoo/addons/hr_holidays_security/README.rst
odoo/addons/hr_holidays_security/__init__.py
odoo/addons/hr_holidays_security/__manifest__.py
odoo/addons/hr_holidays_security/i18n/es.po
odoo/addons/hr_holidays_security/i18n/hr_holidays_security.pot
odoo/addons/hr_holidays_security/models/__init__.py
odoo/addons/hr_holidays_security/models/hr_leave.py
odoo/addons/hr_holidays_security/models/hr_leave_allocation.py
odoo/addons/hr_holidays_security/models/ir_actions_act_window.py
odoo/addons/hr_holidays_security/readme/CONTEXT.md
odoo/addons/hr_holidays_security/readme/CONTRIBUTORS.md
odoo/addons/hr_holidays_security/readme/DESCRIPTION.md
odoo/addons/hr_holidays_security/readme/USAGE.md
odoo/addons/hr_holidays_security/security/security.xml
odoo/addons/hr_holidays_security/static/description/icon.png
odoo/addons/hr_holidays_security/static/description/index.html
odoo/addons/hr_holidays_security/tests/__init__.py
odoo/addons/hr_holidays_security/tests/test_hr_holidays_security.py
odoo/addons/hr_holidays_security/views/hr_leave_allocation_views.xml
odoo/addons/hr_holidays_security/views/hr_leave_views.xml
odoo14_addon_hr_holidays_security-14.0.1.1.0.dist-info/METADATA
odoo14_addon_hr_holidays_security-14.0.1.1.0.dist-info/WHEEL
odoo14_addon_hr_holidays_security-14.0.1.1.0.dist-info/top_level.txt
odoo14_addon_hr_holidays_security-14.0.1.1.0.dist-info/RECORD
